github_status_checker/__init__.py
github_status_checker/__main__.py
github_status_checker/api.py
github_status_checker/controllers/__init__.py
github_status_checker/controllers/commands.py
github_status_checker/models/__init__.py
github_status_checker/models/affected_component.py
github_status_checker/models/component.py
github_status_checker/models/component_status.py
github_status_checker/models/incident.py
github_status_checker/models/incident_update.py
github_status_checker/models/page.py
github_status_checker/models/scheduled_maintenance.py
github_status_checker/models/status.py
github_status_checker/models/summary.py
tests/__init__.py
tests/test.py
github_status_checker-1.0.2.dist-info/LICENSE
github_status_checker-1.0.2.dist-info/METADATA
github_status_checker-1.0.2.dist-info/WHEEL
github_status_checker-1.0.2.dist-info/entry_points.txt
github_status_checker-1.0.2.dist-info/top_level.txt
github_status_checker-1.0.2.dist-info/RECORD
