Metadata-Version: 2.1
Name: github-status-checker
Version: 1.0.2
Summary: Python module/tool for checking the status of GitHub.
Home-page: https://github.com/rapid7/github-status-checker
Author: Rapid7 Integration Alliance
Author-email: integrationalliance@rapid7.com
License: MIT
Platform: UNKNOWN
Classifier: Programming Language :: Python :: 3
Classifier: Operating System :: OS Independent
Classifier: Intended Audience :: Developers
Classifier: Intended Audience :: End Users/Desktop
Classifier: Intended Audience :: System Administrators
Classifier: License :: OSI Approved :: MIT License
Classifier: Natural Language :: English
Classifier: Topic :: Software Development :: Build Tools
Classifier: Topic :: Software Development :: Libraries :: Python Modules
Classifier: Topic :: Software Development :: Version Control :: Git
Classifier: Topic :: System :: Networking :: Monitoring
Requires-Dist: requests (~=2.0)
